CHANGES.txt
CONTRIBUTORS.txt
MANIFEST.in
README.txt
setup.cfg
setup.py
Products/__init__.py
Products.PloneSlimbox.egg-info/PKG-INFO
Products.PloneSlimbox.egg-info/SOURCES.txt
Products.PloneSlimbox.egg-info/dependency_links.txt
Products.PloneSlimbox.egg-info/entry_points.txt
Products.PloneSlimbox.egg-info/namespace_packages.txt
Products.PloneSlimbox.egg-info/not-zip-safe
Products.PloneSlimbox.egg-info/paster_plugins.txt
Products.PloneSlimbox.egg-info/requires.txt
Products.PloneSlimbox.egg-info/top_level.txt
Products/PloneSlimbox/README.txt
Products/PloneSlimbox/__init__.py
Products/PloneSlimbox/config.py
Products/PloneSlimbox/configure.zcml
Products/PloneSlimbox/refresh.txt
Products/PloneSlimbox/version.txt
Products/PloneSlimbox/Extensions/Install.py
Products/PloneSlimbox/Extensions/__init__.py
Products/PloneSlimbox/i18n/slimbox-da.po
Products/PloneSlimbox/i18n/slimbox-de.po
Products/PloneSlimbox/i18n/slimbox-it.po
Products/PloneSlimbox/i18n/slimbox-ja.po
Products/PloneSlimbox/i18n/slimbox-nl.po
Products/PloneSlimbox/i18n/slimbox-no.po
Products/PloneSlimbox/i18n/slimbox-pt-br.po
Products/PloneSlimbox/i18n/slimbox-ru.po
Products/PloneSlimbox/i18n/slimbox-uk.po
Products/PloneSlimbox/i18n/slimbox-zh-tw.po
Products/PloneSlimbox/i18n/slimbox.pot
Products/PloneSlimbox/profiles/default/cssregistry.xml
Products/PloneSlimbox/profiles/default/jsregistry.xml
Products/PloneSlimbox/profiles/default/metadata.xml
Products/PloneSlimbox/profiles/default/skins.xml
Products/PloneSlimbox/skins/plone_slimbox/atct_album_view.pt
Products/PloneSlimbox/skins/plone_slimbox/atct_album_view.pt.metadata
Products/PloneSlimbox/skins/plone_slimbox/atct_album_view21.pt
Products/PloneSlimbox/skins/plone_slimbox/atct_album_view25.pt
Products/PloneSlimbox/skins/plone_slimbox/atct_album_view30.pt
Products/PloneSlimbox/skins/plone_slimbox/atct_album_view32.pt
Products/PloneSlimbox/skins/plone_slimbox/atct_album_view40.pt
Products/PloneSlimbox/skins/plone_slimbox/closelabel.gif
Products/PloneSlimbox/skins/plone_slimbox/get_plone_version.py
Products/PloneSlimbox/skins/plone_slimbox/get_plone_version.py.metadata
Products/PloneSlimbox/skins/plone_slimbox/jquery.min.js
Products/PloneSlimbox/skins/plone_slimbox/lightbox_macros.pt
Products/PloneSlimbox/skins/plone_slimbox/lightbox_title.pt
Products/PloneSlimbox/skins/plone_slimbox/lightbox_title_newsitem.pt
Products/PloneSlimbox/skins/plone_slimbox/loading.gif
