Metadata-Version: 1.0
Name: Products.PloneSlimbox
Version: 0.7.1
Summary: Slimbox(Lightweight Lightbox clone) for atct album view and COREBlog2 attachment image view for Plone.
Home-page: http://plone.org/products/plone-slimbox/
Author: takanori
Author-email: takanori@takanory.net
License: MIT License
Keywords: Plone PloneSlimbox Lightbox Slimbox
Platform: UNKNOWN
Classifier: Framework :: Plone
Classifier: Intended Audience :: Developers
Classifier: Topic :: Software Development :: Libraries :: Python Modules
